coding_open_agent_tools/__init__.py
coding_open_agent_tools/_decorators.py
coding_open_agent_tools/confirmation.py
coding_open_agent_tools/exceptions.py
coding_open_agent_tools/helpers.py
coding_open_agent_tools/types.py
coding_open_agent_tools/advanced_analysis/__init__.py
coding_open_agent_tools/advanced_analysis/detectors.py
coding_open_agent_tools/analysis/__init__.py
coding_open_agent_tools/analysis/ast_parsing.py
coding_open_agent_tools/analysis/complexity.py
coding_open_agent_tools/analysis/imports.py
coding_open_agent_tools/analysis/patterns.py
coding_open_agent_tools/analysis/secrets.py
coding_open_agent_tools/config/__init__.py
coding_open_agent_tools/config/best_practices.py
coding_open_agent_tools/config/env.py
coding_open_agent_tools/config/extraction.py
coding_open_agent_tools/config/formats.py
coding_open_agent_tools/config/security.py
coding_open_agent_tools/config/validation.py
coding_open_agent_tools/cpp/__init__.py
coding_open_agent_tools/cpp/navigation.py
coding_open_agent_tools/csharp/__init__.py
coding_open_agent_tools/csharp/navigation.py
coding_open_agent_tools/database/__init__.py
coding_open_agent_tools/database/operations.py
coding_open_agent_tools/database/query_builder.py
coding_open_agent_tools/database/schema.py
coding_open_agent_tools/database/utils.py
coding_open_agent_tools/dependencies/__init__.py
coding_open_agent_tools/dependencies/analysis.py
coding_open_agent_tools/git/__init__.py
coding_open_agent_tools/git/branches.py
coding_open_agent_tools/git/commits.py
coding_open_agent_tools/git/config.py
coding_open_agent_tools/git/conflicts.py
coding_open_agent_tools/git/diffs.py
coding_open_agent_tools/git/health.py
coding_open_agent_tools/git/history.py
coding_open_agent_tools/git/hooks.py
coding_open_agent_tools/git/remotes.py
coding_open_agent_tools/git/security.py
coding_open_agent_tools/git/status.py
coding_open_agent_tools/git/submodules.py
coding_open_agent_tools/git/tags.py
coding_open_agent_tools/git/workflows.py
coding_open_agent_tools-0.14.1.dist-info/licenses/LICENSE
coding_open_agent_tools-0.14.1.dist-info/METADATA
coding_open_agent_tools-0.14.1.dist-info/WHEEL
coding_open_agent_tools-0.14.1.dist-info/top_level.txt
coding_open_agent_tools-0.14.1.dist-info/RECORD
