Metadata-Version: 2.4
Name: coding-open-agent-tools
Version: 0.14.1
Summary: Advanced code generation and shell scripting toolkit for AI agents, complementing basic-open-agent-tools with development-focused capabilities.
Author-email: Open Agent Tools <unseriousai@gmail.com>
Project-URL: Homepage, https://github.com/Open-Agent-Tools/coding-open-agent-tools
Project-URL: Documentation, https://github.com/Open-Agent-Tools/coding-open-agent-tools#readme
Project-URL: Repository, https://github.com/Open-Agent-Tools/coding-open-agent-tools
Project-URL: Issues, https://github.com/Open-Agent-Tools/coding-open-agent-tools/issues
Keywords: ai,agents,code-generation,shell-scripts,development-tools,automation,scaffolding
Classifier: Development Status :: 1 - Planning
Classifier: Environment :: Console
Classifier: Intended Audience :: Developers
Classifier: License :: OSI Approved :: MIT License
Classifier: Natural Language :: English
Classifier: Operating System :: OS Independent
Classifier: Programming Language :: Python :: 3
Classifier: Programming Language :: Python :: 3.9
Classifier: Programming Language :: Python :: 3.10
Classifier: Programming Language :: Python :: 3.11
Classifier: Programming Language :: Python :: 3.12
Classifier: Topic :: Communications :: Chat
Classifier: Topic :: Scientific/Engineering :: Artificial Intelligence
Classifier: Topic :: Software Development :: Code Generators
Classifier: Topic :: Software Development :: Libraries :: Application Frameworks
Classifier: Topic :: Software Development :: Libraries :: Python Modules
Classifier: Topic :: System :: Shells
Classifier: Typing :: Typed
Requires-Python: >=3.9
License-File: LICENSE
Provides-Extra: all
Requires-Dist: esprima>=4.0.0; extra == "all"
Requires-Dist: tree-sitter-language-pack>=0.13.0; extra == "all"
Requires-Dist: PyYAML>=6.0.0; extra == "all"
Requires-Dist: tomli>=2.0.0; python_version < "3.11" and extra == "all"
Requires-Dist: jsonschema>=4.0.0; extra == "all"
Requires-Dist: packaging>=21.0; extra == "all"
Requires-Dist: detect-secrets>=1.5.0; extra == "all"
Provides-Extra: javascript
Requires-Dist: esprima>=4.0.0; extra == "javascript"
Provides-Extra: java
Requires-Dist: tree-sitter-language-pack>=0.13.0; extra == "java"
Provides-Extra: go
Requires-Dist: tree-sitter-language-pack>=0.13.0; extra == "go"
Provides-Extra: rust
Requires-Dist: tree-sitter-language-pack>=0.13.0; extra == "rust"
Provides-Extra: cpp
Requires-Dist: tree-sitter-language-pack>=0.13.0; extra == "cpp"
Provides-Extra: csharp
Requires-Dist: tree-sitter-language-pack>=0.13.0; extra == "csharp"
Provides-Extra: ruby
Requires-Dist: tree-sitter-language-pack>=0.13.0; extra == "ruby"
Provides-Extra: config
Requires-Dist: PyYAML>=6.0.0; extra == "config"
Requires-Dist: tomli>=2.0.0; python_version < "3.11" and extra == "config"
Requires-Dist: jsonschema>=4.0.0; extra == "config"
Requires-Dist: packaging>=21.0; extra == "config"
Provides-Extra: config-security
Requires-Dist: detect-secrets>=1.5.0; extra == "config-security"
Provides-Extra: strands
Requires-Dist: strands-agents>=1.20.0; extra == "strands"
Requires-Dist: anthropic>=0.25.0; extra == "strands"
Requires-Dist: python-dotenv>=1.0.0; extra == "strands"
Provides-Extra: dev
Requires-Dist: pytest>=9.0.0; extra == "dev"
Requires-Dist: pytest-cov>=7.0.0; extra == "dev"
Requires-Dist: pytest-asyncio>=0.21.0; extra == "dev"
Requires-Dist: ruff>=0.14.0; extra == "dev"
Requires-Dist: mypy>=1.19.0; extra == "dev"
Requires-Dist: pre-commit>=3.0.0; extra == "dev"
Requires-Dist: freezegun>=1.2.0; extra == "dev"
Requires-Dist: google-adk>=0.1.0; extra == "dev"
Requires-Dist: esprima>=4.0.0; extra == "dev"
Requires-Dist: tree-sitter-language-pack>=0.13.0; extra == "dev"
Requires-Dist: PyYAML>=6.0.0; extra == "dev"
Requires-Dist: tomli>=2.0.0; python_version < "3.11" and extra == "dev"
Requires-Dist: jsonschema>=4.0.0; extra == "dev"
Requires-Dist: packaging>=21.0; extra == "dev"
Requires-Dist: detect-secrets>=1.5.0; extra == "dev"
Requires-Dist: strands-agents>=1.20.0; extra == "dev"
Requires-Dist: anthropic>=0.25.0; extra == "dev"
Requires-Dist: python-dotenv>=1.0.0; extra == "dev"
Provides-Extra: test
Requires-Dist: pytest>=9.0.0; extra == "test"
Requires-Dist: pytest-cov>=7.0.0; extra == "test"
Requires-Dist: pytest-asyncio>=0.21.0; extra == "test"
Requires-Dist: freezegun>=1.2.0; extra == "test"
Requires-Dist: google-adk>=0.1.0; extra == "test"
Dynamic: license-file
